
<node players='10' value='0.6'>
	<node action='Extractor' players='1' value='1'>
	</node>
	<node action='SpawningPool' players='3' value='0.667'>
		<node action='Game over' players='1' value='0'>
		</node>
		<node action='Extractor' players='2' value='1'>
		</node>
	</node>
	<node action='Hatchery' players='6' value='0.5'>
		<node action='SpawningPool' players='6' value='0.5'>
			<node action='Extractor' players='6' value='0.5'>
				<node action='Extractor' players='1' value='1'>
				</node>
				<node action='MetabolicBoost' players='4' value='0.5'>
					<node action='Spire' players='2' value='0.5'>
						<node action='Extractor' players='1' value='1'>
						</node>
						<node action='CreepColony' players='1' value='0'>
						</node>
					</node>
					<node action='CreepColony' players='1' value='1'>
					</node>
					<node action='Hatchery' players='1' value='0'>
					</node>
				</node>
				<node action='Hatchery' players='1' value='0'>
				</node>
			</node>
		</node>
	</node>
</node>