
<node players='8' value='0.5'>
	<node action='Pylon' players='8' value='0.5'>
		<node action='Gateway' players='7' value='0.429'>
			<node action='Gateway' players='4' value='0.25'>
				<node action='Pylon' players='4' value='0.25'>
					<node action='CyberneticsCore' players='1' value='0'>
					</node>
					<node action='Pylon' players='3' value='0.333'>
						<node action='Assimilator' players='2' value='0.5'>
							<node action='CyberneticsCore' players='2' value='0.5'>
								<node action='Assimilator' players='1' value='0'>
								</node>
								<node action='Pylon' players='1' value='1'>
								</node>
							</node>
						</node>
						<node action='Pylon' players='1' value='0'>
						</node>
					</node>
				</node>
			</node>
			<node action='Assimilator' players='3' value='0.667'>
				<node action='CyberneticsCore' players='2' value='0.5'>
					<node action='Pylon' players='2' value='0.5'>
						<node action='Stargate' players='1' value='1'>
						</node>
						<node action='SingularityCharge' players='1' value='0'>
						</node>
					</node>
				</node>
				<node action='Forge' players='1' value='1'>
				</node>
			</node>
		</node>
		<node action='Assimilator' players='1' value='1'>
		</node>
	</node>
</node>